{
  "verified": "Artwork Verified",
  "title": "SUNDAY, UNBOTHERED",
  "archiveId": "GLA-SNDNBD-L-002",
  "internalId": "GLA-SNDNBD-L-002-UPFRV62A",
  "edition": "02 / 10",
  "editionNumber": 2,
  "editionTotal": 10,
  "artist": "GLAMOPH",
  "medium": "Archival pigment print on fine art paper",
  "size": "24 × 30 in (L)",
  "frame": "Black",
  "archiveDate": "April 30, 2026",
  "archiveUrl": "https://verify.glamoph.com/GLA-SNDNBD-L-002",
  "ownerArchiveUrl": "https://verify.glamoph.com/GLA-SNDNBD-L-002?t=1ef07efb2d94",
  "image": "/images/SNDNBD.jpg",
  "artworkCode": "SNDNBD",
  "sizeCode": "L",
  "shopifyOrderId": 6143666880596,
  "orderName": "#1044",
  "lineItemId": 14579748634708,
  "sku": "GLAMOPH-SNDNBD-L-BLK",
  "createdAt": "2026-04-30T22:15:00+09:00",
  "updatedAt": "2026-04-30T13:15:12.084Z",
  "ownerToken": "1ef07efb2d94",
  "customerEmail": "campbell.can.xxx@gmail.com",
  "customerFirstName": "yasuyuki",
  "customerLastName": "matsushima",
  "locale": "ja-jp",
  "shippingCountryCode": "JP",
  "billingCountryCode": "JP",
  "permanentArchiveUrl": "https://archive.glamoph.com/records/GLA-SNDNBD-L-002-UPFRV62A/index.html",
  "pdfUrl": "https://archive.glamoph.com/records/GLA-SNDNBD-L-002-UPFRV62A/certificate.pdf"
}
